AUTHORS.md
CHANGES.md
LICENSE
MANIFEST.in
README.md
setup.cfg
setup.py
storlever.ini
storlever_dev.ini
docs/arch.png
docs/arch.vsd
docs/dependency.rst
docs/installation.rst
docs/api/api-nas.rst
docs/api/api-overview.rst
docs/api/api-san.rst
docs/api/api-system.rst
docs/api/api-utils.rst
initscripts/storlever
storlever/__init__.py
storlever/app.py
storlever.egg-info/PKG-INFO
storlever.egg-info/SOURCES.txt
storlever.egg-info/dependency_links.txt
storlever.egg-info/entry_points.txt
storlever.egg-info/not-zip-safe
storlever.egg-info/requires.txt
storlever.egg-info/top_level.txt
storlever/lib/__init__.py
storlever/lib/command.py
storlever/lib/config.py
storlever/lib/confparse.py
storlever/lib/exception.py
storlever/lib/lock.py
storlever/lib/logger.py
storlever/lib/schema.py
storlever/lib/security.py
storlever/lib/utils.py
storlever/mngr/__init__.py
storlever/mngr/block/__init__.py
storlever/mngr/block/blockmgr.py
storlever/mngr/block/scsimgr.py
storlever/mngr/block/iscsi/__init__.py
storlever/mngr/block/iscsi/iface.py
storlever/mngr/block/iscsi/initiatormgr.py
storlever/mngr/block/iscsi/node.py
storlever/mngr/block/lvm/__init__.py
storlever/mngr/block/lvm/lvm.py
storlever/mngr/block/lvm/lvm2app.py
storlever/mngr/block/md/__init__.py
storlever/mngr/block/md/md.py
storlever/mngr/fs/__init__.py
storlever/mngr/fs/ext4.py
storlever/mngr/fs/fs.py
storlever/mngr/fs/fsmgr.py
storlever/mngr/fs/nfs.py
storlever/mngr/fs/xfs.py
storlever/mngr/nas/__init__.py
storlever/mngr/nas/ftpmgr.py
storlever/mngr/nas/nfsmgr.py
storlever/mngr/nas/smbmgr.py
storlever/mngr/network/__init__.py
storlever/mngr/network/bond.py
storlever/mngr/network/dnsmgr.py
storlever/mngr/network/ifconfig.py
storlever/mngr/network/ifmgr.py
storlever/mngr/network/netif.py
storlever/mngr/network/route.py
storlever/mngr/san/__init__.py
storlever/mngr/san/tgt/__init__.py
storlever/mngr/san/tgt/target.py
storlever/mngr/san/tgt/tgtadmparse.py
storlever/mngr/san/tgt/tgtmgr.py
storlever/mngr/system/__init__.py
storlever/mngr/system/cfgmgr.py
storlever/mngr/system/modulemgr.py
storlever/mngr/system/servicemgr.py
storlever/mngr/system/sysinfo.py
storlever/mngr/system/usermgr.py
storlever/mngr/system/webconfig.py
storlever/mngr/utils/__init__.py
