Metadata-Version: 1.0
Name: storlever
Version: 0.1.1
Summary: Management/Configure System for network and storage resource in linux system, with RESTful API
Home-page: https://github.com/OpenSight/StorLever
Author: OpenSight
Author-email: UNKNOWN
License: AGPLv3
Keywords: storage restful web
Platform: UNKNOWN
Classifier: Development Status :: 4 - Beta
Classifier: Framework :: Pyramid
Classifier: Intended Audience :: System Administrators
Classifier: Intended Audience :: Developers
Classifier: License :: OSI Approved :: GNU Affero General Public License v3
Classifier: Operating System :: POSIX :: Linux
Classifier: Programming Language :: Python
Classifier: Programming Language :: Python :: 2.6
Classifier: Programming Language :: Python :: 2.7
Classifier: Topic :: Internet :: WWW/HTTP
Classifier: Topic :: Internet :: WWW/HTTP :: WSGI :: Application
Classifier: Topic :: System :: Monitoring
Classifier: Topic :: System :: Networking :: Monitoring
Classifier: Topic :: System :: Systems Administration
